VDBforGenAI/VectorDatabase.py
VDBforGenAI/__init__.py
VDBforGenAI/Utilities/Loading.py
VDBforGenAI/Utilities/StringUtilities.py
VDBforGenAI/Utilities/__init__.py
VDBforGenAI/VectorisationAndIndexCreation/SearchFunctions.py
VDBforGenAI/VectorisationAndIndexCreation/__init__.py
VectorDatabase/VectorDatabase.py
VectorDatabase/__init__.py
VectorDatabase/Utilities/Loading.py
VectorDatabase/Utilities/StringUtilities.py
VectorDatabase/Utilities/__init__.py
VectorDatabase/VectorisationAndIndexCreation/SearchFunctions.py
VectorDatabase/VectorisationAndIndexCreation/__init__.py
VDBforGenAI-0.23.dist-info/LICENSE
VDBforGenAI-0.23.dist-info/METADATA
VDBforGenAI-0.23.dist-info/WHEEL
VDBforGenAI-0.23.dist-info/top_level.txt
VDBforGenAI-0.23.dist-info/RECORD
