Metadata-Version: 2.1
Name: VDBforGenAI
Version: 0.23
Summary: A simple package for generating and querying Vector Databases for Generative AI as well any other reason
Home-page: https://github.com/JakubJDolezal/VDBforGenAI
Author: Jakub Dolezal
Author-email: jakubdolezal93@gmail.com
Keywords: Vector Database,Generative AI
Classifier: Programming Language :: Python :: 3
Classifier: License :: OSI Approved :: MIT License
Classifier: Operating System :: OS Independent
Requires-Python: >=3.6
License-File: LICENSE
Requires-Dist: faiss-cpu
Requires-Dist: transformers
Requires-Dist: torch
Requires-Dist: numpy
Requires-Dist: PyPDF2
Requires-Dist: docx
Requires-Dist: python-docx
